<spanGrp ana="ClarinSegments"><span from="#t1" to="#t23" type="Sseg" xml:id="S1" /><span from="#t24" to="#t28" type="Sseg" xml:id="S2" /><span from="#t29" to="#t34" type="Sseg" xml:id="S3" /><span from="#t35" to="#t46" type="Sseg" xml:id="S4" /><span from="#t47" to="#t78" type="Sseg" xml:id="S5" /><span from="#t79" to="#t84" type="Sseg" xml:id="S6" /><span from="#t85" to="#t250" type="Sseg" xml:id="S7" /><span from="#t251" to="#t258" type="Sseg" xml:id="S8" /><span from="#t259" to="#t262" type="Sseg" xml:id="S9" /><span from="#t263" to="#t267" type="Sseg" xml:id="S10" /><span from="#t268" to="#t303" type="Sseg" xml:id="S11" /><span from="#t304" to="#t461" type="Sseg" xml:id="S12" /><span from="#t462" to="#t483" type="Sseg" xml:id="S13" /><span from="#t484" to="#t654" type="Sseg" xml:id="S14" /><span from="#t655" to="#t659" type="Sseg" xml:id="S15" /><span from="#t660" to="#t719" type="Sseg" xml:id="S16" /><span from="#t720" to="#t865" type="Sseg" xml:id="S17" /><span from="#t866" to="#t951" type="Sseg" xml:id="S18" /><span from="#t952" to="#t952" type="Sseg" xml:id="S19" /><span from="#t953" to="#t964" type="Sseg" xml:id="S20" /><span from="#t965" to="#t1123" type="Sseg" xml:id="S21" /><span from="#t1124" to="#t1244" type="Sseg" xml:id="S22" /><span from="#t1245" to="#t1277" type="Sseg" xml:id="S23" /><span from="#t1278" to="#t1368" type="Sseg" xml:id="S24" /><span from="#t1369" to="#t1402" type="Sseg" xml:id="S25" /><span from="#t1403" to="#t1418" type="Sseg" xml:id="S26" /><span from="#t1419" to="#t1501" type="Sseg" xml:id="S27" /><span from="#t1502" to="#t1508" type="Sseg" xml:id="S28" /><span from="#t1509" to="#t1578" type="Sseg" xml:id="S29" /><span from="#t1579" to="#t2119" type="Sseg" xml:id="S30" /><span from="#t2120" to="#t2417" type="Sseg" xml:id="S31" /><span from="#t2418" to="#t2700" type="Sseg" xml:id="S32" /><span from="#t2701" to="#t2747" type="Sseg" xml:id="S33" /><span from="#t2748" to="#t2930" type="Sseg" xml:id="S34" /><span from="#t2931" to="#t3171" type="Sseg" xml:id="S35" /><span from="#t3172" to="#t3185" type="Sseg" xml:id="S36" /><span from="#t3186" to="#t3444" type="Sseg" xml:id="S37" /><span from="#t3445" to="#t3582" type="Sseg" xml:id="S38" /><span from="#t3583" to="#t3600" type="Sseg" xml:id="S39" /><span from="#t3601" to="#t3628" type="Sseg" xml:id="S40" /><span from="#t3629" to="#t3719" type="Sseg" xml:id="S41" /><span from="#t3720" to="#t3733" type="Sseg" xml:id="S42" /><span from="#t3734" to="#t3871" type="Sseg" xml:id="S43" /><span from="#t3872" to="#t3887" type="Sseg" xml:id="S44" /><span from="#t3888" to="#t3958" type="Sseg" xml:id="S45" /><span from="#t3959" to="#t4073" type="Sseg" xml:id="S46" /><span from="#t4074" to="#t4170" type="Sseg" xml:id="S47" /><span from="#t4171" to="#t4439" type="Sseg" xml:id="S48" /><span from="#t4440" to="#t4493" type="Sseg" xml:id="S49" /><span from="#t4494" to="#t4548" type="Sseg" xml:id="S50" /><span from="#t4549" to="#t4898" type="Sseg" xml:id="S51" /><span from="#t4899" to="#t4903" type="Sseg" xml:id="S52" /><span from="#t4904" to="#t4925" type="Sseg" xml:id="S53" /><span from="#t4926" to="#t5093" type="Sseg" xml:id="S54" /><span from="#t5094" to="#t5098" type="Sseg" xml:id="S55" /><span from="#t5099" to="#t5102" type="Sseg" xml:id="S56" /><span from="#t5103" to="#t5105" type="Sseg" xml:id="S57" /><span from="#t5106" to="#t5109" type="Sseg" xml:id="S58" /><span from="#t5110" to="#t5121" type="Sseg" xml:id="S59" /><span from="#t5122" to="#t5173" type="Sseg" xml:id="S60" /><span from="#t5174" to="#t5393" type="Sseg" xml:id="S61" /><span from="#t5394" to="#t5415" type="Sseg" xml:id="S62" /><span from="#t5416" to="#t5559" type="Sseg" xml:id="S63" /><span from="#t5560" to="#t5644" type="Sseg" xml:id="S64" /><span from="#t5645" to="#t5725" type="Sseg" xml:id="S65" /><span from="#t5726" to="#t5733" type="Sseg" xml:id="S66" /><span from="#t5734" to="#t5736" type="Sseg" xml:id="S67" /><span from="#t5737" to="#t5744" type="Sseg" xml:id="S68" /><span from="#t5745" to="#t5786" type="Sseg" xml:id="S69" /><span from="#t5787" to="#t5893" type="Sseg" xml:id="S70" /><span from="#t5894" to="#t6059" type="Sseg" xml:id="S71" /><span from="#t6060" to="#t6063" type="Sseg" xml:id="S72" /><span from="#t6064" to="#t6068" type="Sseg" xml:id="S73" /><span from="#t6069" to="#t6082" type="Sseg" xml:id="S74" /><span from="#t6083" to="#t6104" type="Sseg" xml:id="S75" /><span from="#t6105" to="#t6259" type="Sseg" xml:id="S76" /><span from="#t6260" to="#t6455" type="Sseg" xml:id="S77" /><span from="#t6456" to="#t6490" type="Sseg" xml:id="S78" /><span from="#t6491" to="#t6510" type="Sseg" xml:id="S79" /><span from="#t6511" to="#t6514" type="Sseg" xml:id="S80" /><span from="#t6515" to="#t6790" type="Sseg" xml:id="S81" /><span from="#t6791" to="#t6806" type="Sseg" xml:id="S82" /><span from="#t6807" to="#t6868" type="Sseg" xml:id="S83" /><span from="#t6869" to="#t6874" type="Sseg" xml:id="S84" /><span from="#t6875" to="#t6992" type="Sseg" xml:id="S85" /><span from="#t6993" to="#t7021" type="Sseg" xml:id="S86" /><span from="#t7022" to="#t7119" type="Sseg" xml:id="S87" /><span from="#t7120" to="#t7157" type="Sseg" xml:id="S88" /><span from="#t7158" to="#t7172" type="Sseg" xml:id="S89" /><span from="#t7173" to="#t7251" type="Sseg" xml:id="S90" /><span from="#t7252" to="#t7424" type="Sseg" xml:id="S91" /><span from="#t7425" to="#t7526" type="Sseg" xml:id="S92" /><span from="#t7527" to="#t7534" type="Sseg" xml:id="S93" /><span from="#t7535" to="#t7788" type="Sseg" xml:id="S94" /><span from="#t7789" to="#t7881" type="Sseg" xml:id="S95" /><span from="#t7882" to="#t8028" type="Sseg" xml:id="S96" /><span from="#t8029" to="#t8096" type="Sseg" xml:id="S97" /><span from="#t8097" to="#t8175" type="Sseg" xml:id="S98" /><span from="#t8176" to="#t8231" type="Sseg" xml:id="S99" /><span from="#t8232" to="#t8245" type="Sseg" xml:id="S100" /><span from="#t8246" to="#t8303" type="Sseg" xml:id="S101" /><span from="#t8304" to="#t8382" type="Sseg" xml:id="S102" /><span from="#t8383" to="#t8407" type="Sseg" xml:id="S103" /><span from="#t8408" to="#t8620" type="Sseg" xml:id="S104" /><span from="#t8621" to="#t8625" type="Sseg" xml:id="S105" /><span from="#t8626" to="#t8682" type="Sseg" xml:id="S106" /><span from="#t8683" to="#t8726" type="Sseg" xml:id="S107" /><span from="#t8727" to="#t8894" type="Sseg" xml:id="S108" /><span from="#t8895" to="#t8910" type="Sseg" xml:id="S109" /><span from="#t8911" to="#t8959" type="Sseg" xml:id="S110" /><span from="#t8960" to="#t8979" type="Sseg" xml:id="S111" /><span from="#t8980" to="#t9004" type="Sseg" xml:id="S112" /><span from="#t9005" to="#t9047" type="Sseg" xml:id="S113" /><span from="#t9048" to="#t9057" type="Sseg" xml:id="S114" /><span from="#t9058" to="#t9060" type="Sseg" xml:id="S115" /><span from="#t9061" to="#t9234" type="Sseg" xml:id="S116" /><span from="#t9235" to="#t9241" type="Sseg" xml:id="S117" /><span from="#t9242" to="#t9250" type="Sseg" xml:id="S118" /><span from="#t9251" to="#t9254" type="Sseg" xml:id="S119" /><span from="#t9255" to="#t9437" type="Sseg" xml:id="S120" /><span from="#t9438" to="#t9800" type="Sseg" xml:id="S121" /><span from="#t9801" to="#t9864" type="Sseg" xml:id="S122" /><span from="#t9865" to="#t9908" type="Sseg" xml:id="S123" /><span from="#t9909" to="#t9944" type="Sseg" xml:id="S124" /><span from="#t9945" to="#t9961" type="Sseg" xml:id="S125" /><span from="#t9962" to="#t9978" type="Sseg" xml:id="S126" /><span from="#t9979" to="#t10017" type="Sseg" xml:id="S127" /><span from="#t10018" to="#t10222" type="Sseg" xml:id="S128" /><span from="#t10223" to="#t10228" type="Sseg" xml:id="S129" /><span from="#t10229" to="#t10232" type="Sseg" xml:id="S130" /><span from="#t10233" to="#t10237" type="Sseg" xml:id="S131" /><span from="#t10238" to="#t10249" type="Sseg" xml:id="S132" /><span from="#t10250" to="#t10264" type="Sseg" xml:id="S133" /><span from="#t10265" to="#t10279" type="Sseg" xml:id="S134" /><span from="#t10280" to="#t10422" type="Sseg" xml:id="S135" /><span from="#t10423" to="#t10428" type="Sseg" xml:id="S136" /><span from="#t10429" to="#t10580" type="Sseg" xml:id="S137" /><span from="#t10581" to="#t10665" type="Sseg" xml:id="S138" /><span from="#t10666" to="#t11034" type="Sseg" xml:id="S139" /><span from="#t11035" to="#t11139" type="Sseg" xml:id="S140" /><span from="#t11140" to="#t11244" type="Sseg" xml:id="S141" /><span from="#t11245" to="#t11381" type="Sseg" xml:id="S142" /><span from="#t11382" to="#t11386" type="Sseg" xml:id="S143" /><span from="#t11387" to="#t11461" type="Sseg" xml:id="S144" /><span from="#t11462" to="#t11467" type="Sseg" xml:id="S145" /><span from="#t11468" to="#t11470" type="Sseg" xml:id="S146" /><span from="#t11471" to="#t11504" type="Sseg" xml:id="S147" /><span from="#t11505" to="#t11534" type="Sseg" xml:id="S148" /><span from="#t11535" to="#t11648" type="Sseg" xml:id="S149" /><span from="#t11649" to="#t11717" type="Sseg" xml:id="S150" /><span from="#t11718" to="#t11860" type="Sseg" xml:id="S151" /><span from="#t11861" to="#t11930" type="Sseg" xml:id="S152" /><span from="#t11931" to="#t11966" type="Sseg" xml:id="S153" /><span from="#t11967" to="#t12019" type="Sseg" xml:id="S154" /><span from="#t12020" to="#t12026" type="Sseg" xml:id="S155" /><span from="#t12027" to="#t12029" type="Sseg" xml:id="S156" /><span from="#t12030" to="#t12101" type="Sseg" xml:id="S157" /><span from="#t12102" to="#t12117" type="Sseg" xml:id="S158" /><span from="#t12118" to="#t12126" type="Sseg" xml:id="S159" /><span from="#t12127" to="#t12136" type="Sseg" xml:id="S160" /><span from="#t12137" to="#t12252" type="Sseg" xml:id="S161" /><span from="#t12253" to="#t12682" type="Sseg" xml:id="S162" /><span from="#t12683" to="#t12708" type="Sseg" xml:id="S163" /><span from="#t12709" to="#t12789" type="Sseg" xml:id="S164" /><span from="#t12790" to="#t13062" type="Sseg" xml:id="S165" /><span from="#t13063" to="#t13082" type="Sseg" xml:id="S166" /><span from="#t13083" to="#t13113" type="Sseg" xml:id="S167" /><span from="#t13114" to="#t13383" type="Sseg" xml:id="S168" /><span from="#t13384" to="#t13413" type="Sseg" xml:id="S169" /><span from="#t13414" to="#t13586" type="Sseg" xml:id="S170" /><span from="#t13587" to="#t13822" type="Sseg" xml:id="S171" /><span from="#t13823" to="#t13829" type="Sseg" xml:id="S172" /><span from="#t13830" to="#t13876" type="Sseg" xml:id="S173" /><span from="#t13877" to="#t13932" type="Sseg" xml:id="S174" /><span from="#t13933" to="#t14057" type="Sseg" xml:id="S175" /><span from="#t14058" to="#t14062" type="Sseg" xml:id="S176" /><span from="#t14063" to="#t14084" type="Sseg" xml:id="S177" /><span from="#t14085" to="#t14133" type="Sseg" xml:id="S178" /><span from="#t14134" to="#t14234" type="Sseg" xml:id="S179" /><span from="#t14235" to="#t14375" type="Sseg" xml:id="S180" /><span from="#t14376" to="#t14397" type="Sseg" xml:id="S181" /><span from="#t14398" to="#t14432" type="Sseg" xml:id="S182" /><span from="#t14433" to="#t14459" type="Sseg" xml:id="S183" /><span from="#t14460" to="#t14465" type="Sseg" xml:id="S184" /><span from="#t14466" to="#t14469" type="Sseg" xml:id="S185" /><span from="#t14470" to="#t14475" type="Sseg" xml:id="S186" /><span from="#t14476" to="#t14493" type="Sseg" xml:id="S187" /><span from="#t14494" to="#t14540" type="Sseg" xml:id="S188" /><span from="#t14541" to="#t14616" type="Sseg" xml:id="S189" /><span from="#t14617" to="#t14619" type="Sseg" xml:id="S190" /><span from="#t14620" to="#t14627" type="Sseg" xml:id="S191" /><span from="#t14628" to="#t14631" type="Sseg" xml:id="S192" /><span from="#t14632" to="#t14766" type="Sseg" xml:id="S193" /><span from="#t14767" to="#t14887" type="Sseg" xml:id="S194" /><span from="#t14888" to="#t14893" type="Sseg" xml:id="S195" /><span from="#t14894" to="#t15055" type="Sseg" xml:id="S196" /><span from="#t15056" to="#t15159" type="Sseg" xml:id="S197" /><span from="#t15160" to="#t15186" type="Sseg" xml:id="S198" /><span from="#t15187" to="#t15202" type="Sseg" xml:id="S199" /><span from="#t15203" to="#t15375" type="Sseg" xml:id="S200" /><span from="#t15376" to="#t15431" type="Sseg" xml:id="S201" /><span from="#t15432" to="#t15434" type="Sseg" xml:id="S202" /><span from="#t15435" to="#t15488" type="Sseg" xml:id="S203" /><span from="#t15489" to="#t15496" type="Sseg" xml:id="S204" /><span from="#t15497" to="#t15531" type="Sseg" xml:id="S205" /><span from="#t15532" to="#t15565" type="Sseg" xml:id="S206" /><span from="#t15566" to="#t15661" type="Sseg" xml:id="S207" /><span from="#t15662" to="#t15687" type="Sseg" xml:id="S208" /><span from="#t15688" to="#t15690" type="Sseg" xml:id="S209" /><span from="#t15691" to="#t15711" type="Sseg" xml:id="S210" /><span from="#t15712" to="#t15758" type="Sseg" xml:id="S211" /><span from="#t15759" to="#t15786" type="Sseg" xml:id="S212" /><span from="#t15787" to="#t15823" type="Sseg" xml:id="S213" /><span from="#t15824" to="#t15852" type="Sseg" xml:id="S214" /><span from="#t15853" to="#t15870" type="Sseg" xml:id="S215" /><span from="#t15871" to="#t15874" type="Sseg" xml:id="S216" /><span from="#t15875" to="#t15877" type="Sseg" xml:id="S217" /><span from="#t15878" to="#t15964" type="Sseg" xml:id="S218" /><span from="#t15965" to="#t15978" type="Sseg" xml:id="S219" /><span from="#t15979" to="#t16460" type="Sseg" xml:id="S220" /><span from="#t16461" to="#t16480" type="Sseg" xml:id="S221" /><span from="#t16481" to="#t16582" type="Sseg" xml:id="S222" /><span from="#t16583" to="#t17037" type="Sseg" xml:id="S223" /><span from="#t17038" to="#t17040" type="Sseg" xml:id="S224" /><span from="#t17041" to="#t17046" type="Sseg" xml:id="S225" /><span from="#t17047" to="#t17074" type="Sseg" xml:id="S226" /><span from="#t17075" to="#t17180" type="Sseg" xml:id="S227" /><span from="#t17181" to="#t17297" type="Sseg" xml:id="S228" /><span from="#t17298" to="#t17313" type="Sseg" xml:id="S229" /><span from="#t17314" to="#t17344" type="Sseg" xml:id="S230" /><span from="#t17345" to="#t17627" type="Sseg" xml:id="S231" /><span from="#t17628" to="#t17633" type="Sseg" xml:id="S232" /><span from="#t17634" to="#t17698" type="Sseg" xml:id="S233" /><span from="#t17699" to="#t17702" type="Sseg" xml:id="S234" /><span from="#t17703" to="#t17769" type="Sseg" xml:id="S235" /><span from="#t17770" to="#t17937" type="Sseg" xml:id="S236" /><span from="#t17938" to="#t18014" type="Sseg" xml:id="S237" /><span from="#t18015" to="#t18029" type="Sseg" xml:id="S238" /><span from="#t18030" to="#t18094" type="Sseg" xml:id="S239" /><span from="#t18095" to="#t18194" type="Sseg" xml:id="S240" /><span from="#t18195" to="#t18370" type="Sseg" xml:id="S241" /><span from="#t18371" to="#t18582" type="Sseg" xml:id="S242" /><span from="#t18583" to="#t18658" type="Sseg" xml:id="S243" /><span from="#t18659" to="#t18685" type="Sseg" xml:id="S244" /><span from="#t18686" to="#t18708" type="Sseg" xml:id="S245" /><span from="#t18709" to="#t18767" type="Sseg" xml:id="S246" /><span from="#t18768" to="#t18778" type="Sseg" xml:id="S247" /><span from="#t18779" to="#t18798" type="Sseg" xml:id="S248" /><span from="#t18799" to="#t18855" type="Sseg" xml:id="S249" /><span from="#t18856" to="#t18867" type="Sseg" xml:id="S250" /><span from="#t18868" to="#t18877" type="Sseg" xml:id="S251" /><span from="#t18878" to="#t19144" type="Sseg" xml:id="S252" /><span from="#t19145" to="#t19246" type="Sseg" xml:id="S253" /><span from="#t19247" to="#t19278" type="Sseg" xml:id="S254" /><span from="#t19279" to="#t19319" type="Sseg" xml:id="S255" /><span from="#t19320" to="#t19336" type="Sseg" xml:id="S256" /><span from="#t19337" to="#t19360" type="Sseg" xml:id="S257" /><span from="#t19361" to="#t19453" type="Sseg" xml:id="S258" /><span from="#t19454" to="#t19631" type="Sseg" xml:id="S259" /><span from="#t19632" to="#t19695" type="Sseg" xml:id="S260" /><span from="#t19696" to="#t19705" type="Sseg" xml:id="S261" /><span from="#t19706" to="#t19805" type="Sseg" xml:id="S262" /><span from="#t19806" to="#t19865" type="Sseg" xml:id="S263" /><span from="#t19866" to="#t19892" type="Sseg" xml:id="S264" /><span from="#t19893" to="#t19941" type="Sseg" xml:id="S265" /><span from="#t19942" to="#t20043" type="Sseg" xml:id="S266" /><span from="#t20044" to="#t20133" type="Sseg" xml:id="S267" /><span from="#t20134" to="#t20164" type="Sseg" xml:id="S268" /><span from="#t20165" to="#t20198" type="Sseg" xml:id="S269" /><span from="#t20199" to="#t20245" type="Sseg" xml:id="S270" /><span from="#t20246" to="#t20267" type="Sseg" xml:id="S271" /><span from="#t20268" to="#t20292" type="Sseg" xml:id="S272" /><span from="#t20293" to="#t20298" type="Sseg" xml:id="S273" /><span from="#t20299" to="#t20313" type="Sseg" xml:id="S274" /><span from="#t20314" to="#t20359" type="Sseg" xml:id="S275" /><span from="#t20360" to="#t20369" type="Sseg" xml:id="S276" /><span from="#t20370" to="#t20432" type="Sseg" xml:id="S277" /><span from="#t20433" to="#t20607" type="Sseg" xml:id="S278" /><span from="#t20608" to="#t20663" type="Sseg" xml:id="S279" /><span from="#t20664" to="#t20695" type="Sseg" xml:id="S280" /><span from="#t20696" to="#t20731" type="Sseg" xml:id="S281" /><span from="#t20732" to="#t20743" type="Sseg" xml:id="S282" /><span from="#t20744" to="#t20788" type="Sseg" xml:id="S283" /><span from="#t20789" to="#t20818" type="Sseg" xml:id="S284" /><span from="#t20819" to="#t20828" type="Sseg" xml:id="S285" /><span from="#t20829" to="#t20856" type="Sseg" xml:id="S286" /><span from="#t20857" to="#t20892" type="Sseg" xml:id="S287" /><span from="#t20893" to="#t21023" type="Sseg" xml:id="S288" /><span from="#t21024" to="#t21059" type="Sseg" xml:id="S289" /><span from="#t21060" to="#t21082" type="Sseg" xml:id="S290" /><span from="#t21083" to="#t21088" type="Sseg" xml:id="S291" /><span from="#t21089" to="#t21107" type="Sseg" xml:id="S292" /><span from="#t21108" to="#t21133" type="Sseg" xml:id="S293" /><span from="#t21134" to="#t21140" type="Sseg" xml:id="S294" /><span from="#t21141" to="#t21156" type="Sseg" xml:id="S295" /><span from="#t21157" to="#t21178" type="Sseg" xml:id="S296" /><span from="#t21179" to="#t21215" type="Sseg" xml:id="S297" /><span from="#t21216" to="#t21320" type="Sseg" xml:id="S298" /><span from="#t21321" to="#t21729" type="Sseg" xml:id="S299" /><span from="#t21730" to="#t21750" type="Sseg" xml:id="S300" /><span from="#t21751" to="#t21770" type="Sseg" xml:id="S301" /><span from="#t21771" to="#t21844" type="Sseg" xml:id="S302" /><span from="#t21845" to="#t22010" type="Sseg" xml:id="S303" /><span from="#t22011" to="#t22039" type="Sseg" xml:id="S304" /><span from="#t22040" to="#t22056" type="Sseg" xml:id="S305" /><span from="#t22057" to="#t22075" type="Sseg" xml:id="S306" /><span from="#t22076" to="#t22103" type="Sseg" xml:id="S307" /><span from="#t22104" to="#t22334" type="Sseg" xml:id="S308" /><span from="#t22335" to="#t22340" type="Sseg" xml:id="S309" /><span from="#t22341" to="#t22466" type="Sseg" xml:id="S310" /><span from="#t22467" to="#t22500" type="Sseg" xml:id="S311" /><span from="#t22501" to="#t22532" type="Sseg" xml:id="S312" /><span from="#t22533" to="#t22536" type="Sseg" xml:id="S313" /><span from="#t22537" to="#t22583" type="Sseg" xml:id="S314" /><span from="#t22584" to="#t22593" type="Sseg" xml:id="S315" /><span from="#t22594" to="#t22599" type="Sseg" xml:id="S316" /><span from="#t22600" to="#t22611" type="Sseg" xml:id="S317" /><span from="#t22612" to="#t22660" type="Sseg" xml:id="S318" /><span from="#t22661" to="#t22731" type="Sseg" xml:id="S319" /><span from="#t22732" to="#t22734" type="Sseg" xml:id="S320" /><span from="#t22735" to="#t22762" type="Sseg" xml:id="S321" /><span from="#t22763" to="#t22768" type="Sseg" xml:id="S322" /><span from="#t22769" to="#t22860" type="Sseg" xml:id="S323" /><span from="#t22861" to="#t22869" type="Sseg" xml:id="S324" /><span from="#t22870" to="#t22886" type="Sseg" xml:id="S325" /><span from="#t22887" to="#t22951" type="Sseg" xml:id="S326" /><span from="#t22952" to="#t22956" type="Sseg" xml:id="S327" /><span from="#t22957" to="#t22971" type="Sseg" xml:id="S328" /><span from="#t22972" to="#t23062" type="Sseg" xml:id="S329" /><span from="#t23063" to="#t23182" type="Sseg" xml:id="S330" /><span from="#t23183" to="#t23377" type="Sseg" xml:id="S331" /><span from="#t23378" to="#t23544" type="Sseg" xml:id="S332" /><span from="#t23545" to="#t23552" type="Sseg" xml:id="S333" /><span from="#t23553" to="#t23697" type="Sseg" xml:id="S334" /><span from="#t23698" to="#t23740" type="Sseg" xml:id="S335" /><span from="#t23741" to="#t23743" type="Sseg" xml:id="S336" /><span from="#t23744" to="#t23762" type="Sseg" xml:id="S337" /><span from="#t23763" to="#t23773" type="Sseg" xml:id="S338" /><span from="#t23774" to="#t23847" type="Sseg" xml:id="S339" /><span from="#t23848" to="#t23940" type="Sseg" xml:id="S340" /><span from="#t23941" to="#t23950" type="Sseg" xml:id="S341" /><span from="#t23951" to="#t23953" type="Sseg" xml:id="S342" /><span from="#t23954" to="#t23989" type="Sseg" xml:id="S343" /><span from="#t23990" to="#t24026" type="Sseg" xml:id="S344" /><span from="#t24027" to="#t24040" type="Sseg" xml:id="S345" /><span from="#t24041" to="#t24221" type="Sseg" xml:id="S346" /><span from="#t24222" to="#t24245" type="Sseg" xml:id="S347" /><span from="#t24246" to="#t24250" type="Sseg" xml:id="S348" /><span from="#t24251" to="#t24257" type="Sseg" xml:id="S349" /><span from="#t24258" to="#t24268" type="Sseg" xml:id="S350" /><span from="#t24269" to="#t24301" type="Sseg" xml:id="S351" /><span from="#t24302" to="#t24304" type="Sseg" xml:id="S352" /><span from="#t24305" to="#t24527" type="Sseg" xml:id="S353" /><span from="#t24528" to="#t24551" type="Sseg" xml:id="S354" /><span from="#t24552" to="#t24858" type="Sseg" xml:id="S355" /><span from="#t24859" to="#t24875" type="Sseg" xml:id="S356" /><span from="#t24876" to="#t24881" type="Sseg" xml:id="S357" /><span from="#t24882" to="#t24918" type="Sseg" xml:id="S358" /><span from="#t24919" to="#t24988" type="Sseg" xml:id="S359" /><span from="#t24989" to="#t25006" type="Sseg" xml:id="S360" /><span from="#t25007" to="#t25035" type="Sseg" xml:id="S361" /><span from="#t25036" to="#t25074" type="Sseg" xml:id="S362" /><span from="#t25075" to="#t25238" type="Sseg" xml:id="S363" /><span from="#t25239" to="#t25246" type="Sseg" xml:id="S364" /><span from="#t25247" to="#t25251" type="Sseg" xml:id="S365" /><span from="#t25252" to="#t25277" type="Sseg" xml:id="S366" /><span from="#t25278" to="#t25462" type="Sseg" xml:id="S367" /><span from="#t25463" to="#t25519" type="Sseg" xml:id="S368" /><span from="#t25520" to="#t25665" type="Sseg" xml:id="S369" /><span from="#t25666" to="#t25684" type="Sseg" xml:id="S370" /><span from="#t25685" to="#t25784" type="Sseg" xml:id="S371" /><span from="#t25785" to="#t25789" type="Sseg" xml:id="S372" /><span from="#t25790" to="#t26052" type="Sseg" xml:id="S373" /><span from="#t26053" to="#t26092" type="Sseg" xml:id="S374" /><span from="#t26093" to="#t26129" type="Sseg" xml:id="S375" /><span from="#t26130" to="#t26166" type="Sseg" xml:id="S376" /><span from="#t26167" to="#t26268" type="Sseg" xml:id="S377" /><span from="#t26269" to="#t26302" type="Sseg" xml:id="S378" /><span from="#t26303" to="#t26369" type="Sseg" xml:id="S379" /><span from="#t26370" to="#t26474" type="Sseg" xml:id="S380" /><span from="#t26475" to="#t26514" type="Sseg" xml:id="S381" /><span from="#t26515" to="#t26522" type="Sseg" xml:id="S382" /><span from="#t26523" to="#t26531" type="Sseg" xml:id="S383" /><span from="#t26532" to="#t26539" type="Sseg" xml:id="S384" /><span from="#t26540" to="#t26571" type="Sseg" xml:id="S385" /><span from="#t26572" to="#t26620" type="Sseg" xml:id="S386" /><span from="#t26621" to="#t26660" type="Sseg" xml:id="S387" /><span from="#t26661" to="#t26662" type="Sseg" xml:id="S388" /><span from="#t26663" to="#t26689" type="Sseg" xml:id="S389" /><span from="#t26690" to="#t26697" type="Sseg" xml:id="S390" /><span from="#t26698" to="#t26765" type="Sseg" xml:id="S391" /><span from="#t26766" to="#t26877" type="Sseg" xml:id="S392" /><span from="#t26878" to="#t26891" type="Sseg" xml:id="S393" /><span from="#t26892" to="#t26898" type="Sseg" xml:id="S394" /><span from="#t26899" to="#t26951" type="Sseg" xml:id="S395" /><span from="#t26952" to="#t26987" type="Sseg" xml:id="S396" /><span from="#t26988" to="#t26990" type="Sseg" xml:id="S397" /><span from="#t26991" to="#t27002" type="Sseg" xml:id="S398" /><span from="#t27003" to="#t27072" type="Sseg" xml:id="S399" /><span from="#t27073" to="#t27079" type="Sseg" xml:id="S400" /><span from="#t27080" to="#t27101" type="Sseg" xml:id="S401" /><span from="#t27102" to="#t27112" type="Sseg" xml:id="S402" /><span from="#t27113" to="#t27125" type="Sseg" xml:id="S403" /><span from="#t27126" to="#t27149" type="Sseg" xml:id="S404" /><span from="#t27150" to="#t27221" type="Sseg" xml:id="S405" /><span from="#t27222" to="#t27303" type="Sseg" xml:id="S406" /><span from="#t27304" to="#t27309" type="Sseg" xml:id="S407" /><span from="#t27310" to="#t27339" type="Sseg" xml:id="S408" /><span from="#t27340" to="#t27357" type="Sseg" xml:id="S409" /><span from="#t27358" to="#t27362" type="Sseg" xml:id="S410" /><span from="#t27363" to="#t27374" type="Sseg" xml:id="S411" /><span from="#t27375" to="#t27392" type="Sseg" xml:id="S412" /><span from="#t27393" to="#t27466" type="Sseg" xml:id="S413" /><span from="#t27467" to="#t27535" type="Sseg" xml:id="S414" /><span from="#t27536" to="#t27559" type="Sseg" xml:id="S415" /><span from="#t27560" to="#t27574" type="Sseg" xml:id="S416" /><span from="#t27575" to="#t27578" type="Sseg" xml:id="S417" /><span from="#t27579" to="#t27589" type="Sseg" xml:id="S418" /><span from="#t27590" to="#t27618" type="Sseg" xml:id="S419" /><span from="#t27619" to="#t27626" type="Sseg" xml:id="S420" /><span from="#t27627" to="#t27757" type="Sseg" xml:id="S421" /><span from="#t27758" to="#t27779" type="Sseg" xml:id="S422" /><span from="#t27780" to="#t27855" type="Sseg" xml:id="S423" /><span from="#t27856" to="#t27943" type="Sseg" xml:id="S424" /><span from="#t27944" to="#t27955" type="Sseg" xml:id="S425" /><span from="#t27956" to="#t27971" type="Sseg" xml:id="S426" /><span from="#t27972" to="#t28098" type="Sseg" xml:id="S427" /><span from="#t28099" to="#t28111" type="Sseg" xml:id="S428" /><span from="#t28112" to="#t28200" type="Sseg" xml:id="S429" /><span from="#t28201" to="#t28217" type="Sseg" xml:id="S430" /><span from="#t28218" to="#t28267" type="Sseg" xml:id="S431" /><span from="#t28268" to="#t28283" type="Sseg" xml:id="S432" /><span from="#t28284" to="#t28348" type="Sseg" xml:id="S433" /><span from="#t28349" to="#t28359" type="Sseg" xml:id="S434" /><span from="#t28360" to="#t28375" type="Sseg" xml:id="S435" /><span from="#t28376" to="#t28449" type="Sseg" xml:id="S436" /><span from="#t28450" to="#t28516" type="Sseg" xml:id="S437" /><span from="#t28517" to="#t28716" type="Sseg" xml:id="S438" /><span from="#t28717" to="#t28760" type="Sseg" xml:id="S439" /><span from="#t28761" to="#t28772" type="Sseg" xml:id="S440" /><span from="#t28773" to="#t28781" type="Sseg" xml:id="S441" /><span from="#t28782" to="#t28804" type="Sseg" xml:id="S442" /><span from="#t28805" to="#t28818" type="Sseg" xml:id="S443" /><span from="#t28819" to="#t28863" type="Sseg" xml:id="S444" /><span from="#t28864" to="#t28940" type="Sseg" xml:id="S445" /><span from="#t28941" to="#t29094" type="Sseg" xml:id="S446" /><span from="#t29095" to="#t29098" type="Sseg" xml:id="S447" /><span from="#t29099" to="#t29103" type="Sseg" xml:id="S448" /><span from="#t29104" to="#t29123" type="Sseg" xml:id="S449" /><span from="#t29124" to="#t29159" type="Sseg" xml:id="S450" /><span from="#t29160" to="#t29504" type="Sseg" xml:id="S451" /><span from="#t29505" to="#t29561" type="Sseg" xml:id="S452" /><span from="#t29562" to="#t29663" type="Sseg" xml:id="S453" /><span from="#t29664" to="#t29729" type="Sseg" xml:id="S454" /><span from="#t29730" to="#t29762" type="Sseg" xml:id="S455" /><span from="#t29763" to="#t29825" type="Sseg" xml:id="S456" /><span from="#t29826" to="#t30129" type="Sseg" xml:id="S457" /><span from="#t30130" to="#t30136" type="Sseg" xml:id="S458" /><span from="#t30137" to="#t30192" type="Sseg" xml:id="S459" /><span from="#t30193" to="#t30250" type="Sseg" xml:id="S460" /><span from="#t30251" to="#t30316" type="Sseg" xml:id="S461" /><span from="#t30317" to="#t30330" type="Sseg" xml:id="S462" /><span from="#t30331" to="#t30376" type="Sseg" xml:id="S463" /><span from="#t30377" to="#t30533" type="Sseg" xml:id="S464" /><span from="#t30534" to="#t30545" type="Sseg" xml:id="S465" /><span from="#t30546" to="#t30562" type="Sseg" xml:id="S466" /><span from="#t30563" to="#t30649" type="Sseg" xml:id="S467" /><span from="#t30650" to="#t30674" type="Sseg" xml:id="S468" /><span from="#t30675" to="#t30737" type="Sseg" xml:id="S469" /><span from="#t30738" to="#t30779" type="Sseg" xml:id="S470" /><span from="#t30780" to="#t30791" type="Sseg" xml:id="S471" /><span from="#t30792" to="#t30853" type="Sseg" xml:id="S472" /><span from="#t30854" to="#t30887" type="Sseg" xml:id="S473" /><span from="#t30888" to="#t30903" type="Sseg" xml:id="S474" /><span from="#t30904" to="#t30968" type="Sseg" xml:id="S475" /><span from="#t30969" to="#t30975" type="Sseg" xml:id="S476" /><span from="#t30976" to="#t31032" type="Sseg" xml:id="S477" /><span from="#t31033" to="#t31053" type="Sseg" xml:id="S478" /><span from="#t31054" to="#t31079" type="Sseg" xml:id="S479" /><span from="#t31080" to="#t31116" type="Sseg" xml:id="S480" /><span from="#t31117" to="#t31122" type="Sseg" xml:id="S481" /><span from="#t31123" to="#t31139" type="Sseg" xml:id="S482" /><span from="#t31140" to="#t31211" type="Sseg" xml:id="S483" /><span from="#t31212" to="#t31224" type="Sseg" xml:id="S484" /><span from="#t31225" to="#t31306" type="Sseg" xml:id="S485" /><span from="#t31307" to="#t31371" type="Sseg" xml:id="S486" /><span from="#t31372" to="#t31378" type="Sseg" xml:id="S487" /><span from="#t31379" to="#t31601" type="Sseg" xml:id="S488" /><span from="#t31602" to="#t31625" type="Sseg" xml:id="S489" /><span from="#t31626" to="#t31628" type="Sseg" xml:id="S490" /><span from="#t31629" to="#t31731" type="Sseg" xml:id="S491" /><span from="#t31732" to="#t31832" type="Sseg" xml:id="S492" /><span from="#t31833" to="#t31862" type="Sseg" xml:id="S493" /><span from="#t31863" to="#t31881" type="Sseg" xml:id="S494" /><span from="#t31882" to="#t31958" type="Sseg" xml:id="S495" /><span from="#t31959" to="#t31961" type="Sseg" xml:id="S496" /><span from="#t31962" to="#t31976" type="Sseg" xml:id="S497" /><span from="#t31977" to="#t31995" type="Sseg" xml:id="S498" /><span from="#t31996" to="#t32066" type="Sseg" xml:id="S499" /><span from="#t32067" to="#t32086" type="Sseg" xml:id="S500" /><span from="#t32087" to="#t32089" type="Sseg" xml:id="S501" /><span from="#t32090" to="#t32093" type="Sseg" xml:id="S502" /><span from="#t32094" to="#t32153" type="Sseg" xml:id="S503" /><span from="#t32154" to="#t32385" type="Sseg" xml:id="S504" /><span from="#t32386" to="#t32435" type="Sseg" xml:id="S505" /><span from="#t32436" to="#t32518" type="Sseg" xml:id="S506" /><span from="#t32519" to="#t32616" type="Sseg" xml:id="S507" /><span from="#t32617" to="#t32620" type="Sseg" xml:id="S508" /><span from="#t32621" to="#t32644" type="Sseg" xml:id="S509" /><span from="#t32645" to="#t32676" type="Sseg" xml:id="S510" /><span from="#t32677" to="#t32714" type="Sseg" xml:id="S511" /><span from="#t32715" to="#t32724" type="Sseg" xml:id="S512" /><span from="#t32725" to="#t32728" type="Sseg" xml:id="S513" /><span from="#t32729" to="#t32795" type="Sseg" xml:id="S514" /><span from="#t32796" to="#t32806" type="Sseg" xml:id="S515" /><span from="#t32807" to="#t32871" type="Sseg" xml:id="S516" /><span from="#t32872" to="#t32894" type="Sseg" xml:id="S517" /><span from="#t32895" to="#t33159" type="Sseg" xml:id="S518" /><span from="#t33160" to="#t33226" type="Sseg" xml:id="S519" /><span from="#t33227" to="#t33238" type="Sseg" xml:id="S520" /><span from="#t33239" to="#t33242" type="Sseg" xml:id="S521" /><span from="#t33243" to="#t33268" type="Sseg" xml:id="S522" /><span from="#t33269" to="#t33452" type="Sseg" xml:id="S523" /><span from="#t33453" to="#t33455" type="Sseg" xml:id="S524" /><span from="#t33456" to="#t33458" type="Sseg" xml:id="S525" /><span from="#t33459" to="#t33480" type="Sseg" xml:id="S526" /><span from="#t33481" to="#t33727" type="Sseg" xml:id="S527" /><span from="#t33728" to="#t33800" type="Sseg" xml:id="S528" /><span from="#t33801" to="#t33808" type="Sseg" xml:id="S529" /><span from="#t33809" to="#t34042" type="Sseg" xml:id="S530" /><span from="#t34043" to="#t34126" type="Sseg" xml:id="S531" /><span from="#t34127" to="#t34144" type="Sseg" xml:id="S532" /><span from="#t34145" to="#t34149" type="Sseg" xml:id="S533" /><span from="#t34150" to="#t34188" type="Sseg" xml:id="S534" /><span from="#t34189" to="#t34191" type="Sseg" xml:id="S535" /><span from="#t34192" to="#t34202" type="Sseg" xml:id="S536" /><span from="#t34203" to="#t34341" type="Sseg" xml:id="S537" /><span from="#t34342" to="#t34618" type="Sseg" xml:id="S538" /><span from="#t34619" to="#t34658" type="Sseg" xml:id="S539" /><span from="#t34659" to="#t34738" type="Sseg" xml:id="S540" /><span from="#t34739" to="#t34769" type="Sseg" xml:id="S541" /><span from="#t34770" to="#t34908" type="Sseg" xml:id="S542" /><span from="#t34909" to="#t34922" type="Sseg" xml:id="S543" /><span from="#t34923" to="#t35041" type="Sseg" xml:id="S544" /><span from="#t35042" to="#t35158" type="Sseg" xml:id="S545" /><span from="#t35159" to="#t35394" type="Sseg" xml:id="S546" /><span from="#t35395" to="#t35545" type="Sseg" xml:id="S547" /><span from="#t35546" to="#t35576" type="Sseg" xml:id="S548" /><span from="#t35577" to="#t35598" type="Sseg" xml:id="S549" /><span from="#t35599" to="#t35705" type="Sseg" xml:id="S550" /><span from="#t35706" to="#t35739" type="Sseg" xml:id="S551" /><span from="#t35740" to="#t35913" type="Sseg" xml:id="S552" /><span from="#t35914" to="#t35922" type="Sseg" xml:id="S553" /><span from="#t35923" to="#t36054" type="Sseg" xml:id="S554" /><span from="#t36055" to="#t36064" type="Sseg" xml:id="S555" /><span from="#t36065" to="#t36166" type="Sseg" xml:id="S556" /><span from="#t36167" to="#t36227" type="Sseg" xml:id="S557" /><span from="#t36228" to="#t36262" type="Sseg" xml:id="S558" /><span from="#t36263" to="#t36375" type="Sseg" xml:id="S559" /><span from="#t36376" to="#t36411" type="Sseg" xml:id="S560" /><span from="#t36412" to="#t36623" type="Sseg" xml:id="S561" /><span from="#t36624" to="#t36686" type="Sseg" xml:id="S562" /><span from="#t36687" to="#t36697" type="Sseg" xml:id="S563" /><span from="#t36698" to="#t36752" type="Sseg" xml:id="S564" /><span from="#t36753" to="#t36759" type="Sseg" xml:id="S565" /><span from="#t36760" to="#t36841" type="Sseg" xml:id="S566" /><span from="#t36842" to="#t36851" type="Sseg" xml:id="S567" /><span from="#t36852" to="#t36863" type="Sseg" xml:id="S568" /><span from="#t36864" to="#t36948" type="Sseg" xml:id="S569" /><span from="#t36949" to="#t37102" type="Sseg" xml:id="S570" /><span from="#t37103" to="#t37250" type="Sseg" xml:id="S571" /><span from="#t37251" to="#t37256" type="Sseg" xml:id="S572" /><span from="#t37257" to="#t37269" type="Sseg" xml:id="S573" /><span from="#t37270" to="#t37346" type="Sseg" xml:id="S574" /><span from="#t37347" to="#t37654" type="Sseg" xml:id="S575" /><span from="#t37655" to="#t37676" type="Sseg" xml:id="S576" /><span from="#t37677" to="#t37681" type="Sseg" xml:id="S577" /><span from="#t37682" to="#t37711" type="Sseg" xml:id="S578" /><span from="#t37712" to="#t38160" type="Sseg" xml:id="S579" /><span from="#t38161" to="#t38229" type="Sseg" xml:id="S580" /><span from="#t38230" to="#t38254" type="Sseg" xml:id="S581" /><span from="#t38255" to="#t38288" type="Sseg" xml:id="S582" /><span from="#t38289" to="#t38751" type="Sseg" xml:id="S583" /><span from="#t38752" to="#t38820" type="Sseg" xml:id="S584" /><span from="#t38821" to="#t38875" type="Sseg" xml:id="S585" /><span from="#t38876" to="#t38939" type="Sseg" xml:id="S586" /><span from="#t38940" to="#t38992" type="Sseg" xml:id="S587" /><span from="#t38993" to="#t39002" type="Sseg" xml:id="S588" /><span from="#t39003" to="#t39139" type="Sseg" xml:id="S589" /><span from="#t39140" to="#t39218" type="Sseg" xml:id="S590" /><span from="#t39219" to="#t39346" type="Sseg" xml:id="S591" /><span from="#t39347" to="#t39362" type="Sseg" xml:id="S592" /><span from="#t39363" to="#t39524" type="Sseg" xml:id="S593" /><span from="#t39525" to="#t39529" type="Sseg" xml:id="S594" /><span from="#t39530" to="#t39536" type="Sseg" xml:id="S595" /><span from="#t39537" to="#t39766" type="Sseg" xml:id="S596" /><span from="#t39767" to="#t39860" type="Sseg" xml:id="S597" /><span from="#t39861" to="#t39866" type="Sseg" xml:id="S598" /><span from="#t39867" to="#t40001" type="Sseg" xml:id="S599" /><span from="#t40002" to="#t40262" type="Sseg" xml:id="S600" /><span from="#t40263" to="#t40293" type="Sseg" xml:id="S601" /><span from="#t40294" to="#t40543" type="Sseg" xml:id="S602" /><span from="#t40544" to="#t40713" type="Sseg" xml:id="S603" /><span from="#t40714" to="#t41080" type="Sseg" xml:id="S604" /><span from="#t41081" to="#t41092" type="Sseg" xml:id="S605" /><span from="#t41093" to="#t41124" type="Sseg" xml:id="S606" /><span from="#t41125" to="#t41130" type="Sseg" xml:id="S607" /><span from="#t41131" to="#t41189" type="Sseg" xml:id="S608" /><span from="#t41190" to="#t41506" type="Sseg" xml:id="S609" /><span from="#t41507" to="#t41801" type="Sseg" xml:id="S610" /><span from="#t41802" to="#t41828" type="Sseg" xml:id="S611" /><span from="#t41829" to="#t41845" type="Sseg" xml:id="S612" /><span from="#t41846" to="#t41867" type="Sseg" xml:id="S613" /><span from="#t41868" to="#t41957" type="Sseg" xml:id="S614" /><span from="#t41958" to="#t42027" type="Sseg" xml:id="S615" /><span from="#t42028" to="#t42047" type="Sseg" xml:id="S616" /><span from="#t42048" to="#t42181" type="Sseg" xml:id="S617" /><span from="#t42182" to="#t42257" type="Sseg" xml:id="S618" /><span from="#t42258" to="#t42438" type="Sseg" xml:id="S619" /><span from="#t42439" to="#t42801" type="Sseg" xml:id="S620" /><span from="#t42802" to="#t43583" type="Sseg" xml:id="S621" /><span from="#t43584" to="#t43602" type="Sseg" xml:id="S622" /><span from="#t43603" to="#t43608" type="Sseg" xml:id="S623" /><span from="#t43609" to="#t43637" type="Sseg" xml:id="S624" /><span from="#t43638" to="#t43920" type="Sseg" xml:id="S625" /><span from="#t43921" to="#t43924" type="Sseg" xml:id="S626" /><span from="#t43925" to="#t43929" type="Sseg" xml:id="S627" /><span from="#t43930" to="#t43951" type="Sseg" xml:id="S628" /><span from="#t43952" to="#t43982" type="Sseg" xml:id="S629" /><span from="#t43983" to="#t44282" type="Sseg" xml:id="S630" /><span from="#t44283" to="#t44347" type="Sseg" xml:id="S631" /><span from="#t44348" to="#t44364" type="Sseg" xml:id="S632" /><span from="#t44365" to="#t44599" type="Sseg" xml:id="S633" /><span from="#t44600" to="#t44627" type="Sseg" xml:id="S634" /><span from="#t44628" to="#t44650" type="Sseg" xml:id="S635" /><span from="#t44651" to="#t44653" type="Sseg" xml:id="S636" /><span from="#t44654" to="#t44657" type="Sseg" xml:id="S637" /><span from="#t44658" to="#t44667" type="Sseg" xml:id="S638" /><span from="#t44668" to="#t44756" type="Sseg" xml:id="S639" /><span from="#t44757" to="#t44760" type="Sseg" xml:id="S640" /><span from="#t44761" to="#t44843" type="Sseg" xml:id="S641" /><span from="#t44844" to="#t44876" type="Sseg" xml:id="S642" /><span from="#t44877" to="#t44923" type="Sseg" xml:id="S643" /><span from="#t44924" to="#t45373" type="Sseg" xml:id="S644" /><span from="#t45374" to="#t45407" type="Sseg" xml:id="S645" /><span from="#t45408" to="#t45461" type="Sseg" xml:id="S646" /><span from="#t45462" to="#t45485" type="Sseg" xml:id="S647" /><span from="#t45486" to="#t45618" type="Sseg" xml:id="S648" /><span from="#t45619" to="#t45864" type="Sseg" xml:id="S649" /><span from="#t45865" to="#t45954" type="Sseg" xml:id="S650" /><span from="#t45955" to="#t46062" type="Sseg" xml:id="S651" /><span from="#t46063" to="#t46325" type="Sseg" xml:id="S652" /><span from="#t46326" to="#t46440" type="Sseg" xml:id="S653" /><span from="#t46441" to="#t46457" type="Sseg" xml:id="S654" /><span from="#t46458" to="#t46588" type="Sseg" xml:id="S655" /><span from="#t46589" to="#t46617" type="Sseg" xml:id="S656" /><span from="#t46618" to="#t46698" type="Sseg" xml:id="S657" /><span from="#t46699" to="#t46711" type="Sseg" xml:id="S658" /><span from="#t46712" to="#t46759" type="Sseg" xml:id="S659" /><span from="#t46760" to="#t46782" type="Sseg" xml:id="S660" /><span from="#t46783" to="#t46806" type="Sseg" xml:id="S661" /><span from="#t46807" to="#t46857" type="Sseg" xml:id="S662" /><span from="#t46858" to="#t46869" type="Sseg" xml:id="S663" /><span from="#t46870" to="#t46938" type="Sseg" xml:id="S664" /><span from="#t46939" to="#t46950" type="Sseg" xml:id="S665" /><span from="#t46951" to="#t46985" type="Sseg" xml:id="S666" /><span from="#t46986" to="#t47095" type="Sseg" xml:id="S667" /><span from="#t47096" to="#t47138" type="Sseg" xml:id="S668" /><span from="#t47139" to="#t47249" type="Sseg" xml:id="S669" /><span from="#t47250" to="#t47381" type="Sseg" xml:id="S670" /><span from="#t47382" to="#t47387" type="Sseg" xml:id="S671" /><span from="#t47388" to="#t47607" type="Sseg" xml:id="S672" /><span from="#t47608" to="#t47649" type="Sseg" xml:id="S673" /><span from="#t47650" to="#t47653" type="Sseg" xml:id="S674" /><span from="#t47654" to="#t47692" type="Sseg" xml:id="S675" /><span from="#t47693" to="#t47732" type="Sseg" xml:id="S676" /><span from="#t47733" to="#t47774" type="Sseg" xml:id="S677" /><span from="#t47775" to="#t47818" type="Sseg" xml:id="S678" /><span from="#t47819" to="#t47852" type="Sseg" xml:id="S679" /><span from="#t47853" to="#t47877" type="Sseg" xml:id="S680" /><span from="#t47878" to="#t47954" type="Sseg" xml:id="S681" /><span from="#t47955" to="#t48378" type="Sseg" xml:id="S682" /><span from="#t48379" to="#t48402" type="Sseg" xml:id="S683" /><span from="#t48403" to="#t48423" type="Sseg" xml:id="S684" /><span from="#t48424" to="#t48450" type="Sseg" xml:id="S685" /><span from="#t48451" to="#t48730" type="Sseg" xml:id="S686" /><span from="#t48731" to="#t48739" type="Sseg" xml:id="S687" /><span from="#t48740" to="#t48770" type="Sseg" xml:id="S688" /><span from="#t48771" to="#t49057" type="Sseg" xml:id="S689" /><span from="#t49058" to="#t49063" type="Sseg" xml:id="S690" /><span from="#t49064" to="#t49143" type="Sseg" xml:id="S691" /><span from="#t49144" to="#t49296" type="Sseg" xml:id="S692" /><span from="#t49297" to="#t49349" type="Sseg" xml:id="S693" /><span from="#t49350" to="#t49358" type="Sseg" xml:id="S694" /><span from="#t49359" to="#t49519" type="Sseg" xml:id="S695" /><span from="#t49520" to="#t49548" type="Sseg" xml:id="S696" /><span from="#t49549" to="#t49633" type="Sseg" xml:id="S697" /><span from="#t49634" to="#t49713" type="Sseg" xml:id="S698" /><span from="#t49714" to="#t49798" type="Sseg" xml:id="S699" /><span from="#t49799" to="#t49802" type="Sseg" xml:id="S700" /><span from="#t49803" to="#t50017" type="Sseg" xml:id="S701" /><span from="#t50018" to="#t50021" type="Sseg" xml:id="S702" /><span from="#t50022" to="#t50256" type="Sseg" xml:id="S703" /><span from="#t50257" to="#t50397" type="Sseg" xml:id="S704" /><span from="#t50398" to="#t50400" type="Sseg" xml:id="S705" /><span from="#t50401" to="#t50408" type="Sseg" xml:id="S706" /><span from="#t50409" to="#t50532" type="Sseg" xml:id="S707" /><span from="#t50533" to="#t50561" type="Sseg" xml:id="S708" /><span from="#t50562" to="#t50642" type="Sseg" xml:id="S709" /><span from="#t50643" to="#t50645" type="Sseg" xml:id="S710" /><span from="#t50646" to="#t50837" type="Sseg" xml:id="S711" /><span from="#t50838" to="#t50988" type="Sseg" xml:id="S712" /><span from="#t50989" to="#t51023" type="Sseg" xml:id="S713" /><span from="#t51024" to="#t51031" type="Sseg" xml:id="S714" /><span from="#t51032" to="#t51040" type="Sseg" xml:id="S715" /><span from="#t51041" to="#t51104" type="Sseg" xml:id="S716" /><span from="#t51105" to="#t51107" type="Sseg" xml:id="S717" /><span from="#t51108" to="#t51117" type="Sseg" xml:id="S718" /><span from="#t51118" to="#t51124" type="Sseg" xml:id="S719" /><span from="#t51125" to="#t51193" type="Sseg" xml:id="S720" /><span from="#t51194" to="#t51198" type="Sseg" xml:id="S721" /><span from="#t51199" to="#t51213" type="Sseg" xml:id="S722" /><span from="#t51214" to="#t51270" type="Sseg" xml:id="S723" /><span from="#t51271" to="#t51312" type="Sseg" xml:id="S724" /><span from="#t51313" to="#t51379" type="Sseg" xml:id="S725" /><span from="#t51380" to="#t51452" type="Sseg" xml:id="S726" /><span from="#t51453" to="#t51749" type="Sseg" xml:id="S727" /><span from="#t51750" to="#t51839" type="Sseg" xml:id="S728" /><span from="#t51840" to="#t51948" type="Sseg" xml:id="S729" /><span from="#t51949" to="#t52070" type="Sseg" xml:id="S730" /><span from="#t52071" to="#t52166" type="Sseg" xml:id="S731" /><span from="#t52167" to="#t52194" type="Sseg" xml:id="S732" /><span from="#t52195" to="#t52210" type="Sseg" xml:id="S733" /><span from="#t52211" to="#t52271" type="Sseg" xml:id="S734" /><span from="#t52272" to="#t52286" type="Sseg" xml:id="S735" /><span from="#t52287" to="#t52631" type="Sseg" xml:id="S736" /><span from="#t52632" to="#t52648" type="Sseg" xml:id="S737" /><span from="#t52649" to="#t52662" type="Sseg" xml:id="S738" /><span from="#t52663" to="#t52678" type="Sseg" xml:id="S739" /><span from="#t52679" to="#t52691" type="Sseg" xml:id="S740" /><span from="#t52692" to="#t52953" type="Sseg" xml:id="S741" /><span from="#t52954" to="#t52970" type="Sseg" xml:id="S742" /><span from="#t52971" to="#t53001" type="Sseg" xml:id="S743" /><span from="#t53002" to="#t53273" type="Sseg" xml:id="S744" /><span from="#t53274" to="#t53279" type="Sseg" xml:id="S745" /><span from="#t53280" to="#t53316" type="Sseg" xml:id="S746" /><span from="#t53317" to="#t53575" type="Sseg" xml:id="S747" /><span from="#t53576" to="#t53730" type="Sseg" xml:id="S748" /><span from="#t53731" to="#t53808" type="Sseg" xml:id="S749" /><span from="#t53809" to="#t53812" type="Sseg" xml:id="S750" /><span from="#t53813" to="#t53856" type="Sseg" xml:id="S751" /><span from="#t53857" to="#t53905" type="Sseg" xml:id="S752" /><span from="#t53906" to="#t53976" type="Sseg" xml:id="S753" /><span from="#t53977" to="#t53989" type="Sseg" xml:id="S754" /><span from="#t53990" to="#t53992" type="Sseg" xml:id="S755" /><span from="#t53993" to="#t53998" type="Sseg" xml:id="S756" /><span from="#t53999" to="#t54011" type="Sseg" xml:id="S757" /><span from="#t54012" to="#t54014" type="Sseg" xml:id="S758" /><span from="#t54015" to="#t54025" type="Sseg" xml:id="S759" /><span from="#t54026" to="#t54044" type="Sseg" xml:id="S760" /><span from="#t54045" to="#t54048" type="Sseg" xml:id="S761" /><span from="#t54049" to="#t54092" type="Sseg" xml:id="S762" /><span from="#t54093" to="#t54161" type="Sseg" xml:id="S763" /><span from="#t54162" to="#t54234" type="Sseg" xml:id="S764" /><span from="#t54235" to="#t54252" type="Sseg" xml:id="S765" /><span from="#t54253" to="#t54401" type="Sseg" xml:id="S766" /><span from="#t54402" to="#t54639" type="Sseg" xml:id="S767" /><span from="#t54640" to="#t55088" type="Sseg" xml:id="S768" /><span from="#t55089" to="#t55144" type="Sseg" xml:id="S769" /><span from="#t55145" to="#t55157" type="Sseg" xml:id="S770" /><span from="#t55158" to="#t55168" type="Sseg" xml:id="S771" /><span from="#t55169" to="#t55218" type="Sseg" xml:id="S772" /><span from="#t55219" to="#t55224" type="Sseg" xml:id="S773" /><span from="#t55225" to="#t55290" type="Sseg" xml:id="S774" /><span from="#t55291" to="#t55317" type="Sseg" xml:id="S775" /><span from="#t55318" to="#t55349" type="Sseg" xml:id="S776" /><span from="#t55350" to="#t55389" type="Sseg" xml:id="S777" /><span from="#t55390" to="#t55530" type="Sseg" xml:id="S778" /><span from="#t55531" to="#t55545" type="Sseg" xml:id="S779" /><span from="#t55546" to="#t56102" type="Sseg" xml:id="S780" /><span from="#t56103" to="#t56127" type="Sseg" xml:id="S781" /><span from="#t56128" to="#t56425" type="Sseg" xml:id="S782" /><span from="#t56426" to="#t56443" type="Sseg" xml:id="S783" /><span from="#t56444" to="#t56471" type="Sseg" xml:id="S784" /><span from="#t56472" to="#t56785" type="Sseg" xml:id="S785" /><span from="#t56786" to="#t57103" type="Sseg" xml:id="S786" /><span from="#t57104" to="#t57155" type="Sseg" xml:id="S787" /><span from="#t57156" to="#t57366" type="Sseg" xml:id="S788" /><span from="#t57367" to="#t57646" type="Sseg" xml:id="S789" /><span from="#t57647" to="#t57653" type="Sseg" xml:id="S790" /><span from="#t57654" to="#t57767" type="Sseg" xml:id="S791" /><span from="#t57768" to="#t57779" type="Sseg" xml:id="S792" /><span from="#t57780" to="#t57816" type="Sseg" xml:id="S793" /><span from="#t57817" to="#t57989" type="Sseg" xml:id="S794" /><span from="#t57990" to="#t58000" type="Sseg" xml:id="S795" /><span from="#t58001" to="#t58004" type="Sseg" xml:id="S796" /><span from="#t58005" to="#t58364" type="Sseg" xml:id="S797" /><span from="#t58365" to="#t58390" type="Sseg" xml:id="S798" /><span from="#t58391" to="#t58696" type="Sseg" xml:id="S799" /><span from="#t58697" to="#t58707" type="Sseg" xml:id="S800" /><span from="#t58708" to="#t58731" type="Sseg" xml:id="S801" /><span from="#t58732" to="#t58747" type="Sseg" xml:id="S802" /><span from="#t58748" to="#t59047" type="Sseg" xml:id="S803" /><span from="#t59048" to="#t59056" type="Sseg" xml:id="S804" /><span from="#t59057" to="#t59092" type="Sseg" xml:id="S805" /><span from="#t59093" to="#t59147" type="Sseg" xml:id="S806" /><span from="#t59148" to="#t59468" type="Sseg" xml:id="S807" /><span from="#t59469" to="#t59476" type="Sseg" xml:id="S808" /><span from="#t59477" to="#t59495" type="Sseg" xml:id="S809" /><span from="#t59496" to="#t59526" type="Sseg" xml:id="S810" /><span from="#t59527" to="#t59713" type="Sseg" xml:id="S811" /><span from="#t59714" to="#t59909" type="Sseg" xml:id="S812" /><span from="#t59910" to="#t59918" type="Sseg" xml:id="S813" /><span from="#t59919" to="#t59924" type="Sseg" xml:id="S814" /><span from="#t59925" to="#t59945" type="Sseg" xml:id="S815" /><span from="#t59946" to="#t60065" type="Sseg" xml:id="S816" /><span from="#t60066" to="#t60253" type="Sseg" xml:id="S817" /><span from="#t60254" to="#t60303" type="Sseg" xml:id="S818" /><span from="#t60304" to="#t60331" type="Sseg" xml:id="S819" /><span from="#t60332" to="#t60432" type="Sseg" xml:id="S820" /><span from="#t60433" to="#t60448" type="Sseg" xml:id="S821" /><span from="#t60449" to="#t60454" type="Sseg" xml:id="S822" /><span from="#t60455" to="#t60696" type="Sseg" xml:id="S823" /><span from="#t60697" to="#t60706" type="Sseg" xml:id="S824" /><span from="#t60707" to="#t61040" type="Sseg" xml:id="S825" /><span from="#t61041" to="#t61043" type="Sseg" xml:id="S826" /><span from="#t61044" to="#t61046" type="Sseg" xml:id="S827" /><span from="#t61047" to="#t61053" type="Sseg" xml:id="S828" /><span from="#t61054" to="#t61409" type="Sseg" xml:id="S829" /><span from="#t61410" to="#t61417" type="Sseg" xml:id="S830" /><span from="#t61418" to="#t61446" type="Sseg" xml:id="S831" /><span from="#t61447" to="#t61483" type="Sseg" xml:id="S832" /><span from="#t61484" to="#t61528" type="Sseg" xml:id="S833" /><span from="#t61529" to="#t61603" type="Sseg" xml:id="S834" /><span from="#t61604" to="#t61612" type="Sseg" xml:id="S835" /><span from="#t61613" to="#t61622" type="Sseg" xml:id="S836" /><span from="#t61623" to="#t61653" type="Sseg" xml:id="S837" /><span from="#t61654" to="#t61656" type="Sseg" xml:id="S838" /><span from="#t61657" to="#t61831" type="Sseg" xml:id="S839" /><span from="#t61832" to="#t61884" type="Sseg" xml:id="S840" /><span from="#t61885" to="#t61890" type="Sseg" xml:id="S841" /><span from="#t61891" to="#t62080" type="Sseg" xml:id="S842" /><span from="#t62081" to="#t62196" type="Sseg" xml:id="S843" /><span from="#t62197" to="#t62439" type="Sseg" xml:id="S844" /><span from="#t62440" to="#t62443" type="Sseg" xml:id="S845" /><span from="#t62444" to="#t62576" type="Sseg" xml:id="S846" /><span from="#t62577" to="#t62641" type="Sseg" xml:id="S847" /><span from="#t62642" to="#t62695" type="Sseg" xml:id="S848" /><span from="#t62696" to="#t62828" type="Sseg" xml:id="S849" /><span from="#t62829" to="#t62844" type="Sseg" xml:id="S850" /><span from="#t62845" to="#t62888" type="Sseg" xml:id="S851" /><span from="#t62889" to="#t62897" type="Sseg" xml:id="S852" /><span from="#t62898" to="#t62904" type="Sseg" xml:id="S853" /><span from="#t62905" to="#t63010" type="Sseg" xml:id="S854" /><span from="#t63011" to="#t63016" type="Sseg" xml:id="S855" /><span from="#t63017" to="#t63215" type="Sseg" xml:id="S856" /><span from="#t63216" to="#t63275" type="Sseg" xml:id="S857" /><span from="#t63276" to="#t63295" type="Sseg" xml:id="S858" /><span from="#t63296" to="#t63338" type="Sseg" xml:id="S859" /><span from="#t63339" to="#t63379" type="Sseg" xml:id="S860" /><span from="#t63380" to="#t63599" type="Sseg" xml:id="S861" /><span from="#t63600" to="#t63636" type="Sseg" xml:id="S862" /><span from="#t63637" to="#t63639" type="Sseg" xml:id="S863" /><span from="#t63640" to="#t63649" type="Sseg" xml:id="S864" /><span from="#t63650" to="#t63652" type="Sseg" xml:id="S865" /><span from="#t63653" to="#t63659" type="Sseg" xml:id="S866" /><span from="#t63660" to="#t63683" type="Sseg" xml:id="S867" /><span from="#t63684" to="#t63702" type="Sseg" xml:id="S868" /><span from="#t63703" to="#t63712" type="Sseg" xml:id="S869" /><span from="#t63713" to="#t63746" type="Sseg" xml:id="S870" /><span from="#t63747" to="#t63970" type="Sseg" xml:id="S871" /><span from="#t63971" to="#t63990" type="Sseg" xml:id="S872" /><span from="#t63991" to="#t64020" type="Sseg" xml:id="S873" /><span from="#t64021" to="#t64189" type="Sseg" xml:id="S874" /><span from="#t64190" to="#t64205" type="Sseg" xml:id="S875" /><span from="#t64206" to="#t64321" type="Sseg" xml:id="S876" /><span from="#t64322" to="#t64391" type="Sseg" xml:id="S877" /><span from="#t64392" to="#t64448" type="Sseg" xml:id="S878" /><span from="#t64449" to="#t64538" type="Sseg" xml:id="S879" /><span from="#t64539" to="#t64664" type="Sseg" xml:id="S880" /><span from="#t64665" to="#t64715" type="Sseg" xml:id="S881" /><span from="#t64716" to="#t64798" type="Sseg" xml:id="S882" /><span from="#t64799" to="#t64885" type="Sseg" xml:id="S883" /><span from="#t64886" to="#t65085" type="Sseg" xml:id="S884" /><span from="#t65086" to="#t65357" type="Sseg" xml:id="S885" /><span from="#t65358" to="#t65368" type="Sseg" xml:id="S886" /><span from="#t65369" to="#t65411" type="Sseg" xml:id="S887" /><span from="#t65412" to="#t65429" type="Sseg" xml:id="S888" /><span from="#t65430" to="#t65468" type="Sseg" xml:id="S889" /><span from="#t65469" to="#t65737" type="Sseg" xml:id="S890" /><span from="#t65738" to="#t65751" type="Sseg" xml:id="S891" /><span from="#t65752" to="#t65778" type="Sseg" xml:id="S892" /><span from="#t65779" to="#t66015" type="Sseg" xml:id="S893" /><span from="#t66016" to="#t66104" type="Sseg" xml:id="S894" /><span from="#t66105" to="#t66110" type="Sseg" xml:id="S895" /><span from="#t66111" to="#t66143" type="Sseg" xml:id="S896" /><span from="#t66144" to="#t66155" type="Sseg" xml:id="S897" /><span from="#t66156" to="#t66202" type="Sseg" xml:id="S898" /><span from="#t66203" to="#t66349" type="Sseg" xml:id="S899" /><span from="#t66350" to="#t66354" type="Sseg" xml:id="S900" /><span from="#t66355" to="#t66501" type="Sseg" xml:id="S901" /><span from="#t66502" to="#t66575" type="Sseg" xml:id="S902" /><span from="#t66576" to="#t66579" type="Sseg" xml:id="S903" /><span from="#t66580" to="#t66732" type="Sseg" xml:id="S904" /><span from="#t66733" to="#t66813" type="Sseg" xml:id="S905" /><span from="#t66814" to="#t66820" type="Sseg" xml:id="S906" /><span from="#t66821" to="#t66825" type="Sseg" xml:id="S907" /><span from="#t66826" to="#t67127" type="Sseg" xml:id="S908" /><span from="#t67128" to="#t67132" type="Sseg" xml:id="S909" /><span from="#t67133" to="#t67225" type="Sseg" xml:id="S910" /><span from="#t67226" to="#t67337" type="Sseg" xml:id="S911" /><span from="#t67338" to="#t67396" type="Sseg" xml:id="S912" /><span from="#t67397" to="#t67405" type="Sseg" xml:id="S913" /><span from="#t67406" to="#t67485" type="Sseg" xml:id="S914" /><span from="#t67486" to="#t67519" type="Sseg" xml:id="S915" /><span from="#t67520" to="#t67567" type="Sseg" xml:id="S916" /><span from="#t67568" to="#t67781" type="Sseg" xml:id="S917" /><span from="#t67782" to="#t67789" type="Sseg" xml:id="S918" /><span from="#t67790" to="#t67828" type="Sseg" xml:id="S919" /><span from="#t67829" to="#t67920" type="Sseg" xml:id="S920" /><span from="#t67921" to="#t67930" type="Sseg" xml:id="S921" /><span from="#t67931" to="#t68145" type="Sseg" xml:id="S922" /><span from="#t68146" to="#t68296" type="Sseg" xml:id="S923" /><span from="#t68297" to="#t68304" type="Sseg" xml:id="S924" /><span from="#t68305" to="#t68317" type="Sseg" xml:id="S925" /><span from="#t68318" to="#t68344" type="Sseg" xml:id="S926" /><span from="#t68345" to="#t68387" type="Sseg" xml:id="S927" /><span from="#t68388" to="#t68527" type="Sseg" xml:id="S928" /><span from="#t68528" to="#t68545" type="Sseg" xml:id="S929" /><span from="#t68546" to="#t68564" type="Sseg" xml:id="S930" /><span from="#t68565" to="#t68669" type="Sseg" xml:id="S931" /><span from="#t68670" to="#t68704" type="Sseg" xml:id="S932" /><span from="#t68705" to="#t68715" type="Sseg" xml:id="S933" /><span from="#t68716" to="#t68736" type="Sseg" xml:id="S934" /><span from="#t68737" to="#t68813" type="Sseg" xml:id="S935" /><span from="#t68814" to="#t68932" type="Sseg" xml:id="S936" /><span from="#t68933" to="#t68937" type="Sseg" xml:id="S937" /><span from="#t68938" to="#t68960" type="Sseg" xml:id="S938" /><span from="#t68961" to="#t69241" type="Sseg" xml:id="S939" /><span from="#t69242" to="#t69306" type="Sseg" xml:id="S940" /><span from="#t69307" to="#t69312" type="Sseg" xml:id="S941" /><span from="#t69313" to="#t69324" type="Sseg" xml:id="S942" /><span from="#t69325" to="#t69331" type="Sseg" xml:id="S943" /><span from="#t69332" to="#t69638" type="Sseg" xml:id="S944" /><span from="#t69639" to="#t69641" type="Sseg" xml:id="S945" /><span from="#t69642" to="#t69646" type="Sseg" xml:id="S946" /><span from="#t69647" to="#t69676" type="Sseg" xml:id="S947" /><span from="#t69677" to="#t69930" type="Sseg" xml:id="S948" /><span from="#t69931" to="#t69955" type="Sseg" xml:id="S949" /><span from="#t69956" to="#t69968" type="Sseg" xml:id="S950" /><span from="#t69969" to="#t69996" type="Sseg" xml:id="S951" /><span from="#t69997" to="#t70109" type="Sseg" xml:id="S952" /><span from="#t70110" to="#t70214" type="Sseg" xml:id="S953" /><span from="#t70215" to="#t70298" type="Sseg" xml:id="S954" /><span from="#t70299" to="#t70311" type="Sseg" xml:id="S955" /><span from="#t70312" to="#t70339" type="Sseg" xml:id="S956" /><span from="#t70340" to="#t70386" type="Sseg" xml:id="S957" /><span from="#t70387" to="#t70434" type="Sseg" xml:id="S958" /><span from="#t70435" to="#t70455" type="Sseg" xml:id="S959" /><span from="#t70456" to="#t70588" type="Sseg" xml:id="S960" /><span from="#t70589" to="#t70615" type="Sseg" xml:id="S961" /><span from="#t70616" to="#t70748" type="Sseg" xml:id="S962" /><span from="#t70749" to="#t70821" type="Sseg" xml:id="S963" /><span from="#t70822" to="#t70907" type="Sseg" xml:id="S964" /><span from="#t70908" to="#t70915" type="Sseg" xml:id="S965" /><span from="#t70916" to="#t70918" type="Sseg" xml:id="S966" /><span from="#t70919" to="#t70985" type="Sseg" xml:id="S967" /><span from="#t70986" to="#t71044" type="Sseg" xml:id="S968" /><span from="#t71045" to="#t71412" type="Sseg" xml:id="S969" /><span from="#t71413" to="#t71422" type="Sseg" xml:id="S970" /><span from="#t71423" to="#t71454" type="Sseg" xml:id="S971" /><span from="#t71455" to="#t71727" type="Sseg" xml:id="S972" /><span from="#t71728" to="#t71743" type="Sseg" xml:id="S973" /><span from="#t71744" to="#t71774" type="Sseg" xml:id="S974" /><span from="#t71775" to="#t71976" type="Sseg" xml:id="S975" /><span from="#t71977" to="#t72181" type="Sseg" xml:id="S976" /><span from="#t72182" to="#t72191" type="Sseg" xml:id="S977" /><span from="#t72192" to="#t72196" type="Sseg" xml:id="S978" /><span from="#t72197" to="#t72310" type="Sseg" xml:id="S979" /><span from="#t72311" to="#t72399" type="Sseg" xml:id="S980" /><span from="#t72400" to="#t72404" type="Sseg" xml:id="S981" /><span from="#t72405" to="#t72650" type="Sseg" xml:id="S982" /><span from="#t72651" to="#t72657" type="Sseg" xml:id="S983" /><span from="#t72658" to="#t72780" type="Sseg" xml:id="S984" /><span from="#t72781" to="#t72786" type="Sseg" xml:id="S985" /><span from="#t72787" to="#t72815" type="Sseg" xml:id="S986" /><span from="#t72816" to="#t73067" type="Sseg" xml:id="S987" /><span from="#t73068" to="#t73203" type="Sseg" xml:id="S988" /><span from="#t73204" to="#t73219" type="Sseg" xml:id="S989" /><span from="#t73220" to="#t73249" type="Sseg" xml:id="S990" /><span from="#t73250" to="#t73697" type="Sseg" xml:id="S991" /><span from="#t73698" to="#t73702" type="Sseg" xml:id="S992" /><span from="#t73703" to="#t73714" type="Sseg" xml:id="S993" /><span from="#t73715" to="#t73734" type="Sseg" xml:id="S994" /><span from="#t73735" to="#t73797" type="Sseg" xml:id="S995" /><span from="#t73798" to="#t73900" type="Sseg" xml:id="S996" /><span from="#t73901" to="#t74177" type="Sseg" xml:id="S997" /><span from="#t74178" to="#t74183" type="Sseg" xml:id="S998" /><span from="#t74184" to="#t74557" type="Sseg" xml:id="S999" /><span from="#t74558" to="#t74560" type="Sseg" xml:id="S1000" /><span from="#t74561" to="#t74933" type="Sseg" xml:id="S1001" /><span from="#t74934" to="#t74937" type="Sseg" xml:id="S1002" /><span from="#t74938" to="#t75029" type="Sseg" xml:id="S1003" /><span from="#t75030" to="#t75342" type="Sseg" xml:id="S1004" /><span from="#t75343" to="#t75347" type="Sseg" xml:id="S1005" /><span from="#t75348" to="#t75351" type="Sseg" xml:id="S1006" /><span from="#t75352" to="#t75380" type="Sseg" xml:id="S1007" /><span from="#t75381" to="#t75758" type="Sseg" xml:id="S1008" /><span from="#t75759" to="#t75762" type="Sseg" xml:id="S1009" /><span from="#t75763" to="#t75781" type="Sseg" xml:id="S1010" /><span from="#t75782" to="#t75812" type="Sseg" xml:id="S1011" /><span from="#t75813" to="#t76025" type="Sseg" xml:id="S1012" /><span from="#t76026" to="#t76208" type="Sseg" xml:id="S1013" /><span from="#t76209" to="#t76224" type="Sseg" xml:id="S1014" /><span from="#t76225" to="#t76357" type="Sseg" xml:id="S1015" /><span from="#t76358" to="#t76534" type="Sseg" xml:id="S1016" /><span from="#t76535" to="#t76541" type="Sseg" xml:id="S1017" /><span from="#t76542" to="#t76546" type="Sseg" xml:id="S1018" /><span from="#t76547" to="#t76553" type="Sseg" xml:id="S1019" /><span from="#t76554" to="#t76661" type="Sseg" xml:id="S1020" /><span from="#t76662" to="#t76666" type="Sseg" xml:id="S1021" /><span from="#t76667" to="#t76900" type="Sseg" xml:id="S1022" /><span from="#t76901" to="#t76909" type="Sseg" xml:id="S1023" /><span from="#t76910" to="#t76914" type="Sseg" xml:id="S1024" /><span from="#t76915" to="#t76943" type="Sseg" xml:id="S1025" /><span from="#t76944" to="#t77402" type="Sseg" xml:id="S1026" /><span from="#t77403" to="#t77431" type="Sseg" xml:id="S1027" /><span from="#t77432" to="#t77484" type="Sseg" xml:id="S1028" /><span from="#t77485" to="#t77502" type="Sseg" xml:id="S1029" /><span from="#t77503" to="#t77531" type="Sseg" xml:id="S1030" /><span from="#t77532" to="#t77844" type="Sseg" xml:id="S1031" /><span from="#t77845" to="#t77861" type="Sseg" xml:id="S1032" /><span from="#t77862" to="#t77927" type="Sseg" xml:id="S1033" /><span from="#t77928" to="#t78054" type="Sseg" xml:id="S1034" /><span from="#t78055" to="#t78105" type="Sseg" xml:id="S1035" /><span from="#t78106" to="#t78118" type="Sseg" xml:id="S1036" /><span from="#t78119" to="#t78127" type="Sseg" xml:id="S1037" /><span from="#t78128" to="#t78223" type="Sseg" xml:id="S1038" /><span from="#t78224" to="#t78228" type="Sseg" xml:id="S1039" /><span from="#t78229" to="#t78406" type="Sseg" xml:id="S1040" /><span from="#t78407" to="#t78445" type="Sseg" xml:id="S1041" /><span from="#t78446" to="#t78559" type="Sseg" xml:id="S1042" /><span from="#t78560" to="#t78624" type="Sseg" xml:id="S1043" /><span from="#t78625" to="#t78653" type="Sseg" xml:id="S1044" /><span from="#t78654" to="#t78739" type="Sseg" xml:id="S1045" /><span from="#t78740" to="#t78839" type="Sseg" xml:id="S1046" /><span from="#t78840" to="#t78851" type="Sseg" xml:id="S1047" /><span from="#t78852" to="#t78941" type="Sseg" xml:id="S1048" /><span from="#t78942" to="#t79352" type="Sseg" xml:id="S1049" /><span from="#t79353" to="#t79355" type="Sseg" xml:id="S1050" /><span from="#t79356" to="#t79359" type="Sseg" xml:id="S1051" /><span from="#t79360" to="#t79390" type="Sseg" xml:id="S1052" /><span from="#t79391" to="#t79714" type="Sseg" xml:id="S1053" /><span from="#t79715" to="#t79769" type="Sseg" xml:id="S1054" /><span from="#t79770" to="#t79781" type="Sseg" xml:id="S1055" /><span from="#t79782" to="#t79812" type="Sseg" xml:id="S1056" /><span from="#t79813" to="#t79962" type="Sseg" xml:id="S1057" /><span from="#t79963" to="#t79990" type="Sseg" xml:id="S1058" /><span from="#t79991" to="#t80282" type="Sseg" xml:id="S1059" /><span from="#t80283" to="#t80297" type="Sseg" xml:id="S1060" /><span from="#t80298" to="#t80332" type="Sseg" xml:id="S1061" /><span from="#t80333" to="#t80344" type="Sseg" xml:id="S1062" /><span from="#t80345" to="#t80434" type="Sseg" xml:id="S1063" /><span from="#t80435" to="#t80824" type="Sseg" xml:id="S1064" /><span from="#t80825" to="#t80827" type="Sseg" xml:id="S1065" /><span from="#t80828" to="#t80834" type="Sseg" xml:id="S1066" /><span from="#t80835" to="#t80864" type="Sseg" xml:id="S1067" /><span from="#t80865" to="#t81048" type="Sseg" xml:id="S1068" /><span from="#t81049" to="#t81060" type="Sseg" xml:id="S1069" /><span from="#t81061" to="#t81091" type="Sseg" xml:id="S1070" /><span from="#t81092" to="#t81409" type="Sseg" xml:id="S1071" /><span from="#t81410" to="#t81491" type="Sseg" xml:id="S1072" /><span from="#t81492" to="#t81536" type="Sseg" xml:id="S1073" /><span from="#t81537" to="#t81620" type="Sseg" xml:id="S1074" /><span from="#t81621" to="#t81738" type="Sseg" xml:id="S1075" /><span from="#t81739" to="#t81741" type="Sseg" xml:id="S1076" /><span from="#t81742" to="#t81891" type="Sseg" xml:id="S1077" /><span from="#t81892" to="#t81906" type="Sseg" xml:id="S1078" /><span from="#t81907" to="#t81914" type="Sseg" xml:id="S1079" /><span from="#t81915" to="#t81943" type="Sseg" xml:id="S1080" /><span from="#t81944" to="#t81998" type="Sseg" xml:id="S1081" /><span from="#t81999" to="#t82024" type="Sseg" xml:id="S1082" /><span from="#t82025" to="#t82044" type="Sseg" xml:id="S1083" /><span from="#t82045" to="#t82047" type="Sseg" xml:id="S1084" /><span from="#t82048" to="#t82056" type="Sseg" xml:id="S1085" /><span from="#t82057" to="#t82134" type="Sseg" xml:id="S1086" /><span from="#t82135" to="#t82142" type="Sseg" xml:id="S1087" /><span from="#t82143" to="#t82192" type="Sseg" xml:id="S1088" /><span from="#t82193" to="#t82309" type="Sseg" xml:id="S1089" /><span from="#t82310" to="#t82318" type="Sseg" xml:id="S1090" /><span from="#t82319" to="#t82334" type="Sseg" xml:id="S1091" /><span from="#t82335" to="#t82372" type="Sseg" xml:id="S1092" /><span from="#t82373" to="#t82439" type="Sseg" xml:id="S1093" /><span from="#t82440" to="#t82738" type="Sseg" xml:id="S1094" /><span from="#t82739" to="#t82745" type="Sseg" xml:id="S1095" /><span from="#t82746" to="#t82778" type="Sseg" xml:id="S1096" /><span from="#t82779" to="#t82889" type="Sseg" xml:id="S1097" /><span from="#t82890" to="#t82990" type="Sseg" xml:id="S1098" /><span from="#t82991" to="#t82999" type="Sseg" xml:id="S1099" /><span from="#t83000" to="#t83031" type="Sseg" xml:id="S1100" /><span from="#t83032" to="#t83181" type="Sseg" xml:id="S1101" /><span from="#t83182" to="#t83251" type="Sseg" xml:id="S1102" /><span from="#t83252" to="#t83403" type="Sseg" xml:id="S1103" /><span from="#t83404" to="#t83460" type="Sseg" xml:id="S1104" /><span from="#t83461" to="#t83466" type="Sseg" xml:id="S1105" /><span from="#t83467" to="#t83559" type="Sseg" xml:id="S1106" /><span from="#t83560" to="#t83619" type="Sseg" xml:id="S1107" /><span from="#t83620" to="#t83669" type="Sseg" xml:id="S1108" /><span from="#t83670" to="#t83675" type="Sseg" xml:id="S1109" /><span from="#t83676" to="#t83688" type="Sseg" xml:id="S1110" /><span from="#t83689" to="#t83696" type="Sseg" xml:id="S1111" /><span from="#t83697" to="#t83738" type="Sseg" xml:id="S1112" /><span from="#t83739" to="#t83758" type="Sseg" xml:id="S1113" /><span from="#t83759" to="#t83872" type="Sseg" xml:id="S1114" /><span from="#t83873" to="#t83880" type="Sseg" xml:id="S1115" /><span from="#t83881" to="#t83970" type="Sseg" xml:id="S1116" /><span from="#t83971" to="#t84037" type="Sseg" xml:id="S1117" /><span from="#t84038" to="#t84325" type="Sseg" xml:id="S1118" /><span from="#t84326" to="#t84475" type="Sseg" xml:id="S1119" /><span from="#t84476" to="#t84481" type="Sseg" xml:id="S1120" /><span from="#t84482" to="#t84512" type="Sseg" xml:id="S1121" /><span from="#t84513" to="#t84528" type="Sseg" xml:id="S1122" /><span from="#t84529" to="#t84700" type="Sseg" xml:id="S1123" /><span from="#t84701" to="#t84747" type="Sseg" xml:id="S1124" /><span from="#t84748" to="#t84765" type="Sseg" xml:id="S1125" /><span from="#t84766" to="#t84779" type="Sseg" xml:id="S1126" /><span from="#t84780" to="#t84808" type="Sseg" xml:id="S1127" /><span from="#t84809" to="#t85033" type="Sseg" xml:id="S1128" /><span from="#t85034" to="#t85497" type="Sseg" xml:id="S1129" /><span from="#t85498" to="#t85593" type="Sseg" xml:id="S1130" /><span from="#t85594" to="#t85732" type="Sseg" xml:id="S1131" /><span from="#t85733" to="#t86152" type="Sseg" xml:id="S1132" /><span from="#t86153" to="#t86158" type="Sseg" xml:id="S1133" /><span from="#t86159" to="#t86189" type="Sseg" xml:id="S1134" /><span from="#t86190" to="#t86409" type="Sseg" xml:id="S1135" /><span from="#t86410" to="#t86424" type="Sseg" xml:id="S1136" /><span from="#t86425" to="#t86455" type="Sseg" xml:id="S1137" /><span from="#t86456" to="#t86613" type="Sseg" xml:id="S1138" /><span from="#t86614" to="#t86734" type="Sseg" xml:id="S1139" /><span from="#t86735" to="#t86745" type="Sseg" xml:id="S1140" /><span from="#t86746" to="#t86751" type="Sseg" xml:id="S1141" /><span from="#t86752" to="#t86779" type="Sseg" xml:id="S1142" /><span from="#t86780" to="#t86798" type="Sseg" xml:id="S1143" /><span from="#t86799" to="#t86852" type="Sseg" xml:id="S1144" /><span from="#t86853" to="#t86938" type="Sseg" xml:id="S1145" /><span from="#t86939" to="#t86948" type="Sseg" xml:id="S1146" /><span from="#t86949" to="#t87136" type="Sseg" xml:id="S1147" /><span from="#t87137" to="#t87184" type="Sseg" xml:id="S1148" /><span from="#t87185" to="#t87245" type="Sseg" xml:id="S1149" /><span from="#t87246" to="#t87287" type="Sseg" xml:id="S1150" /><span from="#t87288" to="#t87358" type="Sseg" xml:id="S1151" /><span from="#t87359" to="#t87437" type="Sseg" xml:id="S1152" /><span from="#t87438" to="#t87533" type="Sseg" xml:id="S1153" /><span from="#t87534" to="#t87621" type="Sseg" xml:id="S1154" /><span from="#t87622" to="#t87639" type="Sseg" xml:id="S1155" /><span from="#t87640" to="#t87699" type="Sseg" xml:id="S1156" /><span from="#t87700" to="#t87822" type="Sseg" xml:id="S1157" /><span from="#t87823" to="#t87842" type="Sseg" xml:id="S1158" /><span from="#t87843" to="#t87856" type="Sseg" xml:id="S1159" /><span from="#t87857" to="#t87907" type="Sseg" xml:id="S1160" /><span from="#t87908" to="#t88031" type="Sseg" xml:id="S1161" /><span from="#t88032" to="#t88156" type="Sseg" xml:id="S1162" /><span from="#t88157" to="#t88197" type="Sseg" xml:id="S1163" /><span from="#t88198" to="#t88213" type="Sseg" xml:id="S1164" /><span from="#t88214" to="#t88287" type="Sseg" xml:id="S1165" /><span from="#t88288" to="#t88303" type="Sseg" xml:id="S1166" /><span from="#t88304" to="#t88307" type="Sseg" xml:id="S1167" /><span from="#t88308" to="#t88320" type="Sseg" xml:id="S1168" /><span from="#t88321" to="#t88347" type="Sseg" xml:id="S1169" /><span from="#t88348" to="#t88356" type="Sseg" xml:id="S1170" /><span from="#t88357" to="#t88387" type="Sseg" xml:id="S1171" /><span from="#t88388" to="#t88687" type="Sseg" xml:id="S1172" /><span from="#t88688" to="#t88698" type="Sseg" xml:id="S1173" /><span from="#t88699" to="#t88732" type="Sseg" xml:id="S1174" /><span from="#t88733" to="#t88911" type="Sseg" xml:id="S1175" /><span from="#t88912" to="#t89329" type="Sseg" xml:id="S1176" /><span from="#t89330" to="#t89527" type="Sseg" xml:id="S1177" /><span from="#t89528" to="#t89533" type="Sseg" xml:id="S1178" /><span from="#t89534" to="#t89543" type="Sseg" xml:id="S1179" /><span from="#t89544" to="#t89578" type="Sseg" xml:id="S1180" /><span from="#t89579" to="#t89795" type="Sseg" xml:id="S1181" /><span from="#t89796" to="#t89820" type="Sseg" xml:id="S1182" /><span from="#t89821" to="#t89824" type="Sseg" xml:id="S1183" /><span from="#t89825" to="#t89830" type="Sseg" xml:id="S1184" /><span from="#t89831" to="#t89888" type="Sseg" xml:id="S1185" /><span from="#t89889" to="#t89914" type="Sseg" xml:id="S1186" /><span from="#t89915" to="#t89943" type="Sseg" xml:id="S1187" /><span from="#t89944" to="#t90248" type="Sseg" xml:id="S1188" /><span from="#t90249" to="#t90315" type="Sseg" xml:id="S1189" /><span from="#t90316" to="#t90322" type="Sseg" xml:id="S1190" /><span from="#t90323" to="#t90338" type="Sseg" xml:id="S1191" /><span from="#t90339" to="#t90443" type="Sseg" xml:id="S1192" /><span from="#t90444" to="#t90472" type="Sseg" xml:id="S1193" /><span from="#t90473" to="#t90494" type="Sseg" xml:id="S1194" /><span from="#t90495" to="#t90514" type="Sseg" xml:id="S1195" /><span from="#t90515" to="#t90556" type="Sseg" xml:id="S1196" /><span from="#t90557" to="#t90696" type="Sseg" xml:id="S1197" /><span from="#t90697" to="#t90742" type="Sseg" xml:id="S1198" /><span from="#t90743" to="#t90780" type="Sseg" xml:id="S1199" /><span from="#t90781" to="#t90787" type="Sseg" xml:id="S1200" /><span from="#t90788" to="#t90825" type="Sseg" xml:id="S1201" /><span from="#t90826" to="#t90828" type="Sseg" xml:id="S1202" /><span from="#t90829" to="#t90865" type="Sseg" xml:id="S1203" /><span from="#t90866" to="#t90894" type="Sseg" xml:id="S1204" /><span from="#t90895" to="#t90904" type="Sseg" xml:id="S1205" /><span from="#t90905" to="#t90914" type="Sseg" xml:id="S1206" /><span from="#t90915" to="#t90985" type="Sseg" xml:id="S1207" /><span from="#t90986" to="#t91133" type="Sseg" xml:id="S1208" /><span from="#t91134" to="#t91497" type="Sseg" xml:id="S1209" /><span from="#t91498" to="#t91505" type="Sseg" xml:id="S1210" /><span from="#t91506" to="#t91530" type="Sseg" xml:id="S1211" /><span from="#t91531" to="#t91565" type="Sseg" xml:id="S1212" /><span from="#t91566" to="#t91912" type="Sseg" xml:id="S1213" /><span from="#t91913" to="#t91920" type="Sseg" xml:id="S1214" /><span from="#t91921" to="#t91952" type="Sseg" xml:id="S1215" /><span from="#t91953" to="#t92134" type="Sseg" xml:id="S1216" /><span from="#t92135" to="#t92146" type="Sseg" xml:id="S1217" /><span from="#t92147" to="#t92174" type="Sseg" xml:id="S1218" /><span from="#t92175" to="#t92244" type="Sseg" xml:id="S1219" /><span from="#t92245" to="#t92352" type="Sseg" xml:id="S1220" /><span from="#t92353" to="#t92384" type="Sseg" xml:id="S1221" /><span from="#t92385" to="#t92463" type="Sseg" xml:id="S1222" /><span from="#t92464" to="#t92585" type="Sseg" xml:id="S1223" /><span from="#t92586" to="#t92619" type="Sseg" xml:id="S1224" /><span from="#t92620" to="#t92839" type="Sseg" xml:id="S1225" /><span from="#t92840" to="#t92949" type="Sseg" xml:id="S1226" /><span from="#t92950" to="#t92956" type="Sseg" xml:id="S1227" /><span from="#t92957" to="#t92992" type="Sseg" xml:id="S1228" /><span from="#t92993" to="#t93066" type="Sseg" xml:id="S1229" /><span from="#t93067" to="#t93242" type="Sseg" xml:id="S1230" /><span from="#t93243" to="#t93245" type="Sseg" xml:id="S1231" /><span from="#t93246" to="#t93259" type="Sseg" xml:id="S1232" /><span from="#t93260" to="#t93290" type="Sseg" xml:id="S1233" /><span from="#t93291" to="#t93530" type="Sseg" xml:id="S1234" /><span from="#t93531" to="#t93585" type="Sseg" xml:id="S1235" /><span from="#t93586" to="#t93621" type="Sseg" xml:id="S1236" /><span from="#t93622" to="#t93659" type="Sseg" xml:id="S1237" /><span from="#t93660" to="#t93698" type="Sseg" xml:id="S1238" /><span from="#t93699" to="#t93754" type="Sseg" xml:id="S1239" /><span from="#t93755" to="#t93813" type="Sseg" xml:id="S1240" /><span from="#t93814" to="#t93890" type="Sseg" xml:id="S1241" /><span from="#t93891" to="#t93906" type="Sseg" xml:id="S1242" /><span from="#t93907" to="#t94009" type="Sseg" xml:id="S1243" /><span from="#t94010" to="#t94049" type="Sseg" xml:id="S1244" /><span from="#t94050" to="#t94115" type="Sseg" xml:id="S1245" /><span from="#t94116" to="#t94125" type="Sseg" xml:id="S1246" /><span from="#t94126" to="#t94212" type="Sseg" xml:id="S1247" /><span from="#t94213" to="#t94264" type="Sseg" xml:id="S1248" /><span from="#t94265" to="#t94268" type="Sseg" xml:id="S1249" /><span from="#t94269" to="#t94376" type="Sseg" xml:id="S1250" /><span from="#t94377" to="#t94411" type="Sseg" xml:id="S1251" /><span from="#t94412" to="#t94497" type="Sseg" xml:id="S1252" /><span from="#t94498" to="#t94678" type="Sseg" xml:id="S1253" /><span from="#t94679" to="#t94753" type="Sseg" xml:id="S1254" /><span from="#t94754" to="#t94780" type="Sseg" xml:id="S1255" /><span from="#t94781" to="#t94903" type="Sseg" xml:id="S1256" /><span from="#t94904" to="#t94942" type="Sseg" xml:id="S1257" /><span from="#t94943" to="#t94983" type="Sseg" xml:id="S1258" /><span from="#t94984" to="#t95148" type="Sseg" xml:id="S1259" /><span from="#t95149" to="#t95152" type="Sseg" xml:id="S1260" /><span from="#t95153" to="#t95168" type="Sseg" xml:id="S1261" /><span from="#t95169" to="#t95205" type="Sseg" xml:id="S1262" /><span from="#t95206" to="#t95238" type="Sseg" xml:id="S1263" /><span from="#t95239" to="#t95283" type="Sseg" xml:id="S1264" /><span from="#t95284" to="#t95326" type="Sseg" xml:id="S1265" /><span from="#t95327" to="#t95331" type="Sseg" xml:id="S1266" /><span from="#t95332" to="#t95335" type="Sseg" xml:id="S1267" /><span from="#t95336" to="#t95470" type="Sseg" xml:id="S1268" /><span from="#t95471" to="#t95750" type="Sseg" xml:id="S1269" /><span from="#t95751" to="#t95829" type="Sseg" xml:id="S1270" /><span from="#t95830" to="#t95836" type="Sseg" xml:id="S1271" /><span from="#t95837" to="#t95885" type="Sseg" xml:id="S1272" /><span from="#t95886" to="#t95888" type="Sseg" xml:id="S1273" /><span from="#t95889" to="#t95921" type="Sseg" xml:id="S1274" /><span from="#t95922" to="#t95950" type="Sseg" xml:id="S1275" /><span from="#t95951" to="#t96062" type="Sseg" xml:id="S1276" /><span from="#t96063" to="#t96076" type="Sseg" xml:id="S1277" /><span from="#t96077" to="#t96081" type="Sseg" xml:id="S1278" /><span from="#t96082" to="#t96097" type="Sseg" xml:id="S1279" /><span from="#t96098" to="#t96156" type="Sseg" xml:id="S1280" /><span from="#t96157" to="#t96222" type="Sseg" xml:id="S1281" /><span from="#t96223" to="#t96378" type="Sseg" xml:id="S1282" /><span from="#t96379" to="#t96482" type="Sseg" xml:id="S1283" /><span from="#t96483" to="#t96651" type="Sseg" xml:id="S1284" /><span from="#t96652" to="#t96731" type="Sseg" xml:id="S1285" /><span from="#t96732" to="#t96786" type="Sseg" xml:id="S1286" /><span from="#t96787" to="#t96814" type="Sseg" xml:id="S1287" /><span from="#t96815" to="#t97190" type="Sseg" xml:id="S1288" /><span from="#t97191" to="#t97318" type="Sseg" xml:id="S1289" /><span from="#t97319" to="#t97349" type="Sseg" xml:id="S1290" /></spanGrp>
